{
  "project_info": {
    "project_number": "825317241990",
    "project_id": "bauniid1",
    "storage_bucket": "bauniid1.appspot.com"
  },
  "client": [
    {
      "client_info": {
        "mobilesdk_app_id": "1:825317241990:android:904730a357083fe710cd07",
        "android_client_info": {
          "package_name": "com.bauniid1"
        }
      },
      "oauth_client": [],
      "api_key": [
        {
          "current_key": "AIzaSyCu3Vzo72oPvr-UIOcIQrD53OpRmIFJN04"
        }
      ],
      "services": {
        "appinvite_service": {
          "other_platform_oauth_client": []
        }
      }
    }
  ],
  "configuration_version": "1"
}
